_docsweeper/__init__.py
_docsweeper/command_line.py
_docsweeper/command_line.py.orig
_docsweeper/docsweeper.py
_docsweeper/py.typed
_docsweeper/result_handler.py
_docsweeper/util.py
_docsweeper/version_control.py
_docsweeper/version_control.py.orig
docsweeper/__init__.py
docsweeper/py.typed
flake8_plugin/Plugin.py
flake8_plugin/__init__.py
docsweeper-1.2.5.dist-info/entry_points.txt
docsweeper-1.2.5.dist-info/LICENSE
docsweeper-1.2.5.dist-info/WHEEL
docsweeper-1.2.5.dist-info/METADATA
docsweeper-1.2.5.dist-info/RECORD
