Metadata-Version: 2.1
Name: docsweeper
Version: 1.2.5
Summary: A linter for your Python code base that finds potentially outdated docstrings using version control.
Home-page: https://docsweeper.readthedocs.io/
License: MIT
Author: Andreas Thüring
Author-email: a.thuering@gmail.com
Requires-Python: >=3.7,<3.11
Classifier: Development Status :: 5 - Production/Stable
Classifier: Environment :: Console
Classifier: Environment :: Plugins
Classifier: Framework :: Flake8
Classifier: Intended Audience :: Developers
Classifier: License :: OSI Approved :: MIT License
Classifier: Programming Language :: Python :: 3
Classifier: Programming Language :: Python :: 3 :: Only
Classifier: Programming Language :: Python :: 3.10
Classifier: Programming Language :: Python :: 3.7
Classifier: Programming Language :: Python :: 3.8
Classifier: Programming Language :: Python :: 3.8 
Classifier: Programming Language :: Python :: 3.9
Classifier: Topic :: Software Development
Classifier: Topic :: Software Development :: Documentation
Classifier: Topic :: Software Development :: Libraries :: Python Modules
Classifier: Topic :: Software Development :: Quality Assurance
Classifier: Topic :: Software Development :: Testing
Classifier: Topic :: Software Development :: Version Control
Classifier: Topic :: Software Development :: Version Control :: Git
Classifier: Topic :: Software Development :: Version Control :: Mercurial
Classifier: Topic :: Utilities
Requires-Dist: click (>=8.1.0,<9.0.0)
Project-URL: Documentation, https://docsweeper.readthedocs.io/
Project-URL: Repository, https://github.com/thueringa/docsweeper
